setup.py
WidGL/Styles.py
WidGL/Styles_loader.py
WidGL/Widgets.py
WidGL/__init__.py
WidGL/wrapper.py
WidGL.egg-info/PKG-INFO
WidGL.egg-info/SOURCES.txt
WidGL.egg-info/dependency_links.txt
WidGL.egg-info/not-zip-safe
WidGL.egg-info/requires.txt
WidGL.egg-info/top_level.txt