Metadata-Version: 2.1
Name: WidGL
Version: 1.4
Summary: small and compact widgets distributions
Author-email: pvana621@gmail.com
